[
    {
        "name": "John Wick",
        "imdb": 9.8,
        "date": "2022",
        "sposter": "img/Jhon Wick.jpg",
        "bposter": "img/jhon wick1.webp",
        "genre": "Action",
        "type": "movie",
        "url": "jhon wick.html",
        "description": "John Wick is a former hitman grieving the loss of his true love. When his home is broken into, robbed, and his dog killed, he is forced to return to action to exact revenge.",
        "trailer": "video/John Wick.mp4",
        "movie": "video/John Wick.mp4",
        "low": "video/John Wick.mp4",
        "medium": "video/John Wick.mp4",
        "high": "video/John Wick.mp4"
    }, {
    "name": "The Boys",
    "imdb": 9.3,
    "date": "2022",
    "sposter": "img/the boys.jpg",
    "bposter": "img/the boys1.jpg",
    "genre": "Action",
    "type": "series",
    "url": "the boys.html",
    "description":" A group of vigilantes set out to take down corrupt superheroes who abuse their superpowers.",
    "trailer": "video/The Boys.mp4",
    "movie":"video/The Boys.mp4",
    "low": "video/The Boys.mp4",
    "medium": "video/The Boys.mp4",
    "high": "video/The Boys.mp4"
}, {
    "name": "Money Heist",
    "imdb": 9.9,
    "date": "2020",
    "sposter": "img/money heist.jpg",
    "bposter": "img/money heist1.jpg",
    "genre": "Action",
    "type": "series",
    "url": "money heist.html",
    "description":"An unusual group of robbers attempt to carry out the most perfect robbery in Spanish history - stealing 2.4 billion euros from the Royal Mint of Spain.",
    "movie": "video/Money Heist.mp4",
    "trailer": "video/Money Heist.mp4",
    "low": "video/Money Heist.mp4",
    "medium": "video/Money Heist.mp4",
    "high": "video/Money Heist.mp4"
},{
    "name": "Ant Man",
    "imdb": 8.9,
    "date": "2017",
    "sposter": "img/ant man.jpg",
    "bposter": "img/ant man1.jpg",
    "genre": "Action",
    "type": "movie",
    "url": "ant man.html",
    "description":"Armed with a super-suit with the astonishing ability to shrink in scale but increase in strength, cat burglar Scott Lang must embrace his inner hero and help his mentor, Dr. Hank Pym, pull off a plan that will save the world.",
    "trailer": "video/Ant Man.mp4",
    "movie":"video/Ant Man.mp4",
    "low": "video/Ant Man.mp4",
    "medium": "video/Ant Man.mp4",
    "high": "video/Ant Man.mp4"
}, {
    "name": "Avengers",
    "imdb": 9.9,
    "date": "2012",
    "sposter": "img/avengers.jpg",
    "bposter": "img/avengers1.jpg",
    "genre": "Action",
    "type": "movie",
    "url": "avengers.html",
    "description":"Political involvement in the Avengers' affairs causes a rift between Captain America and Iron Man.",
    "trailer": "video/Avengers.mp4",
    "movie":"video/Avengers.mp4",
    "low": "video/Avengers.mp4",
    "medium": "video/Avengers.mp4",
    "high": "video/Avengers.mp4"
}, {
    "name": "Moon Knight",
    "imdb": 7.3,
    "date": "2022",
    "sposter": "img/moon knight.jpg",
    "bposter": "img/moon knight1.webp",
    "genre": "Action",
    "type": "series",
    "url": "moon knight.html",
    "description":"Steven Grant discovers he's been granted the powers of an Egyptian moon god. But he soon finds out that these newfound powers can be both a blessing and a curse to his troubled life.",
    "trailer": "video/Moon Knight.mp4",
    "movie": "video/Moon Knight.mp4",
    "low": "video/Moon Knight.mp4",
    "medium": "video/Moon Knight.mp4",
    "high": "video/Moon Knight.mp4"
}, {
    "name": "Chhakka Panja 5",
    "imdb": 9.6,
    "date": "2024",
    "sposter": "img/chhakka panja5.jpg",
    "bposter": "img/chhakka panja51.png",
    "genre": "Action",
    "type": "Movie",
    "url": "CHHAKKA PANJA.html",
    "description":"Chhakka Panja 5 is a Nepali drama movie starring Deepak Raj Giri, Kedar Ghimire, Buddhi Tamang, Barsh Siwakoti and directed by Deepa Shree Niroula",
    "trailer": "video/CHHAKKA PANJA 5.mp4",
    "movie":"video/CHHAKKA PANJA 5.mp4",
    "low": "video/CHHAKKA PANJA 5.mp4",
    "medium": "video/CHHAKKA PANJA 5.mp4",
    "high": "video/CHHAKKA PANJA 5.mp4"
}, {
    "name": "Behuli from Meghauli",
    "imdb": 7.9,
    "date": "2024",
    "sposter": "img/behuli.jpg",
    "bposter": "img/behuli1.jpg",
    "genre": "Action",
    "type": "Movies",
    "url": "Behuli from Meghauli.html",
    "description":" Behuli from Meghauli is a 2024 Nepalese comedy-drama film written and directed by Sajan Kafle and Aakash Baral.",
    "trailer": "video/BEHULI from MEGHAULI.mp4",
    "movie": "video/BEHULI from MEGHAULI.mp4",
    "low": "video/BEHULI from MEGHAULI.mp4",
    "medium": "video/BEHULI from MEGHAULI.mp4",
    "high": "video/BEHULI from MEGHAULI.mp4"
}, {
    "name": "Thor Love Of Thunder",
    "imdb": 8.8,
    "date": "2021",
    "sposter": "img/thor love of thunder.jpg",
    "bposter": "img/thor love of thunder1.avif",
    "genre": "Action",
    "type": "movie",
    "url": "thor love of thunder.html",
    "description":"Thor enlists the help of Valkyrie, Korg and ex-girlfriend Jane Foster to fight Gorr the God Butcher, who intends to make the gods extinct.",
    "trailer": "video/Thor 5.mp4",
    "movie":"video/Thor 5.mp4",
    "low": "video/Thor 5.mp4",
    "medium": "video/Thor 5.mp4",
    "high": "video/Thor 5.mp4"
}, {
    "name": "12 Gaun",
    "imdb": 9.8,
    "date": "2022",
    "sposter": "img/12gau.jpg",
    "bposter": "img/12gau1.jpg",
    "genre": "Action",
    "type": "movie",
    "url": "12 Gaun.html",
    "description":"A son's quest for vengeance against a tyrannical village chief who murdered his parents. The chief rules through fear, oppressing villagers with his gang, forbidding escape. The son must confront the chief's ruthless reign to seek justice",
    "trailer": "video/12 Gaun.mp4",
    "movie":"video/12 Gaun.mp4",
    "low": "video/12 Gaun.mp4",
    "medium": "video/12 Gaun.mp4",
    "high": "video/12 Gaun.mp4"
}, {
    "name": "shang chi-2",
    "imdb": 8.2,
    "date": "2022",
    "sposter": "img/shang chi-2.webp",
    "bposter": "img/shang chi-21.webp",
    "genre": "Action",
    "type": "movie",
    "url": "Shang-Chi 2.html",
    "description":"Shang-Chi and the Legend of the Ten Rings is a 2021 American superhero film based on Marvel Comics featuring the character Shang-Chi. Produced by Marvel Studios.",
    "trailer": "video/Shang-Chi 2.mp4",
    "movie" :"video/Shang-Chi 2.mp4",
    "low": "video/Shang-Chi 2.mp4",
    "medium": "video/Shang-Chi 2.mp4",
    "high": "video/Shang-Chi 2.mp4"
}, {
    "name": "300 The Rise Of New Empire",
    "imdb": 8.0,
    "date": "2022",
    "sposter": "img/Zack Snyder's 300.jpg",
    "bposter": "img/Zack Snyder's 3001.jpg",
    "genre": "Action",
    "type": "movie",
    "url": "The Rise Of New Empire.html",
    "description":"In the ancient battle of Thermopylae, King Leonidas and 300 Spartans fight against Xerxes and his massive Persian army. They face insurmountable odds when they are betrayed by a Spartan reject.",
    "trailer": "video/Zack Snyder's 300.mp4",
    "movie" :"video/Zack Snyder's 300.mp4",
    "low": "video/Zack Snyder's 300.mp4",
    "medium": "video/Zack Snyder's 300.mp4",
    "high": "video/Zack Snyder's 300.mp4"
}, {
    "name": "The Mummy",
    "imdb": 8.0,
    "date": "2017",
    "sposter": "img/The Mummy.jpg",
    "bposter": "img/The Mummy1.jpg",
    "genre": "Action",
    "type": "movie",
    "url": "The Mummy.html",
    "description": "After Sergeant Nick and Corporal Chris call an air strike on an enemy stronghold, they stumble upon the tomb of Princess Ahmanet. The princess is set free and Nick has to fight for his life.",
    "trailer": "video/The Mummy.mp4",
    "movie":"video/The Mummy.mp4",
    "low": "video/The Mummy.mp4",
    "medium": "video/The Mummy.mp4",
    "high": "video/The Mummy.mp4"
}, {
    "name": "Eternals",
    "imdb": 6.3,
    "date": "2021",
    "sposter": "img/eternals.jpg",
    "bposter": "img/eternals1.webp",
    "genre": "Action",
    "type": "movie",
    "url": "eternals.html",
    "description":"The saga of the Eternals, a race of immortal beings who lived on Earth and shaped its history and civilizations.",
    "trailer": "video/Eternals.mp4",
    "movie": "video/Eternals.mp4",
    "low": "video/Eternals.mp4",
    "medium": "video/Eternals.mp4",
    "high": "video/Eternals.mp4"
}, {
    "name": "Spider Man",
    "imdb": 9.9,
    "date": "2020",
    "sposter": "img/spiderman.jpg",
    "bposter": "img/spiderman1.jpg",
    "genre": "Action",
    "type": "movie",
    "url": "spiderman.html",
    "description":"After being bitten by a genetically-modified spider, a shy teenager gains spider-like abilities that he uses to fight injustice as a masked superhero and face a vengeful enemy.",
    "trailer": "video/Spider-Man.mp4",
    "movie":"video/Spider-Man.mp4",
    "low": "video/Spider-Man.mp4",
    "medium": "video/Spider-Man.mp4",
    "high": "video/Spider-Man.mp4"
}]